torchutils/__init__.py
torchutils/loss/__init__.py
torchutils/loss/combined_loss.py
torchutils/schedulers/__init__.py
torchutils/schedulers/lr_decay.py
torchutils/schedulers/schedulers.py
pytorch_utilities-0.0.2.dist-info/METADATA
pytorch_utilities-0.0.2.dist-info/WHEEL
pytorch_utilities-0.0.2.dist-info/licenses/LICENSE
pytorch_utilities-0.0.2.dist-info/RECORD
